docums_charts_plugin
